p_privacy_qt/EMD.py
p_privacy_qt/SMS.py
p_privacy_qt/__init__.py
p_privacy_qt-0.0.10.dist-info/LICENSE
p_privacy_qt-0.0.10.dist-info/METADATA
p_privacy_qt-0.0.10.dist-info/WHEEL
p_privacy_qt-0.0.10.dist-info/top_level.txt
p_privacy_qt-0.0.10.dist-info/RECORD
